simplerr/__init__.py
simplerr/__main__.py
simplerr/cors.py
simplerr/dispatcher.py
simplerr/errors.py
simplerr/methods.py
simplerr/script.py
simplerr/serialise.py
simplerr/session.py
simplerr/template.py
simplerr/web.py
simplerr-0.17.10.dist-info/METADATA
simplerr-0.17.10.dist-info/WHEEL
simplerr-0.17.10.dist-info/entry_points.txt
simplerr-0.17.10.dist-info/top_level.txt
simplerr-0.17.10.dist-info/RECORD
